AUTHORS
LICENSE
README.rst
dev_requirements.txt
requirements.txt
setup.py
setuptools_dummy-0.1.0.4-py2.7.egg
ella_taggit/.DS_Store
ella_taggit/__init__.py
ella_taggit/models.py
ella_taggit/newman_admin.py
ella_taggit/related_finders.py
ella_taggit/urls.py
ella_taggit/views.py
ella_taggit.egg-info/PKG-INFO
ella_taggit.egg-info/SOURCES.txt
ella_taggit.egg-info/dependency_links.txt
ella_taggit.egg-info/requires.txt
ella_taggit.egg-info/top_level.txt
ella_taggit/locale/cs/LC_MESSAGES/django.mo
ella_taggit/locale/cs/LC_MESSAGES/django.po
ella_taggit/management/__init__.py
ella_taggit/management/commands/__init__.py
ella_taggit/management/commands/migrate_from_ella_tagging.py
ella_taggit/migrations/0001_initial.py
ella_taggit/migrations/__init__.py
ella_taggit/templatetags/__init__.py
ella_taggit/templatetags/ellataggit_tags.py
test_ella_taggit/.DS_Store
test_ella_taggit/__init__.py
test_ella_taggit/manage.py
test_ella_taggit/run_tests.py
test_ella_taggit/test_models.py
test_ella_taggit/test_pagination.py
test_ella_taggit/test_related.py
test_ella_taggit/urls.py
test_ella_taggit/settings/__init__.py
test_ella_taggit/settings/base.py
test_ella_taggit/settings/config.py